<poster>Greys Anatomy</poster>
<fanart>http://images.huffingtonpost.com/2013-12-06-greys.jpg</fanart>

<item>
<title>I Must Have Lost It On the Wind: Episode 1</title>
<thubnail></thumbnail>
<link>http://movreel.com/6qwy97rl1epn</link>
</item>

<item>
<title>Puzzle With a Piece Missing: Episode 2</title>
<thubnail></thumbnail>
<link>http://movreel.com/3pzx99cyvhsn</link>
</item>


<item>
<title>Got to be Real: Episode 3</title>
<thubnail></thumbnail>
<link>http://movreel.com/gv06lg5gv096</link>
</item>


<item>
<title></title>
<thubnail></thumbnail>
<link></link>
</item>


<item>
<title></title>
<thubnail></thumbnail>
<link></link>
</item>


<item>
<title></title>
<thubnail></thumbnail>
<link></link>
</item>


<item>
<title></title>
<thubnail></thumbnail>
<link></link>
</item>


<item>
<title></title>
<thubnail></thumbnail>
<link></link>
</item>


<item>
<title></title>
<thubnail></thumbnail>
<link></link>
</item>


<item>
<title></title>
<thubnail></thumbnail>
<link></link>
</item>


<item>
<title></title>
<thubnail></thumbnail>
<link></link>
</item>



